LICENSE
MANIFEST.in
README.rst
pyproject.toml
fdb/__init__.py
fdb/apiversion.py
fdb/directory_impl.py
fdb/fdboptions.py
fdb/impl.py
fdb/locality.py
fdb/subspace_impl.py
fdb/tenant_management.py
fdb/tuple.py
foundationdb.egg-info/PKG-INFO
foundationdb.egg-info/SOURCES.txt
foundationdb.egg-info/dependency_links.txt
foundationdb.egg-info/top_level.txt