Metadata-Version: 2.4
Name: foundationdb
Version: 7.4.4
Summary: Python bindings for the FoundationDB Database
Author-email: FoundationDB Team <fdb-dist@apple.com>
Project-URL: Homepage, https://www.foundationdb.org
Project-URL: Repository, https://github.com/apple/foundationdb
Keywords: database,key-value store,acid
Classifier: Development Status :: 5 - Production/Stable
Classifier: Intended Audience :: Developers
Classifier: License :: OSI Approved :: Apache Software License
Classifier: Operating System :: MacOS :: MacOS X
Classifier: Operating System :: Microsoft :: Windows
Classifier: Operating System :: POSIX :: Linux
Classifier: Programming Language :: Python :: 3.8
Classifier: Programming Language :: Python :: Implementation :: CPython
Classifier: Topic :: Database
Classifier: Topic :: Database :: Front-Ends
Requires-Python: >=3.8
License-File: LICENSE
Dynamic: license-file
